doxg-0.4.4.dist-info/METADATA
doxg-0.4.4.dist-info/WHEEL
doxg-0.4.4.dist-info/entry_points.txt
doxg/.pytest_cache/.gitignore
doxg/.pytest_cache/CACHEDIR.TAG
doxg/.pytest_cache/README.md
doxg/.pytest_cache/v/cache/nodeids
doxg/.pytest_cache/v/cache/stepwise
doxg/__init__.py
doxg/game.py
doxg-0.4.4.dist-info/RECORD
