Metadata-Version: 2.1
Name: doxg
Version: 0.4.4
Summary: useful contents of mine
Author-Email: doxg <praze74@gmail.com>
License: MIT
Project-URL: Homepage, https://github.com/doxgxxn/doxg
Project-URL: Bug tracker, https://github.com/doxgxxn/doxg/issues
Requires-Python: >=3.8
